odoo/addons/pos_order_line_note/README.rst
odoo/addons/pos_order_line_note/__init__.py
odoo/addons/pos_order_line_note/__manifest__.py
odoo/addons/pos_order_line_note/i18n/fr.po
odoo/addons/pos_order_line_note/i18n/pos_order_line_note.pot
odoo/addons/pos_order_line_note/models/__init__.py
odoo/addons/pos_order_line_note/models/pos_order_line.py
odoo/addons/pos_order_line_note/readme/CONTRIBUTORS.rst
odoo/addons/pos_order_line_note/readme/DESCRIPTION.rst
odoo/addons/pos_order_line_note/readme/ROADMAP.rst
odoo/addons/pos_order_line_note/readme/USAGE.rst
odoo/addons/pos_order_line_note/static/description/icon.png
odoo/addons/pos_order_line_note/static/description/index.html
odoo/addons/pos_order_line_note/static/description/point_of_sale.png
odoo/addons/pos_order_line_note/static/description/pos_order_form.png
odoo/addons/pos_order_line_note/views/view_pos_order.xml
odoo12_addon_pos_order_line_note-12.0.1.0.4.dist-info/METADATA
odoo12_addon_pos_order_line_note-12.0.1.0.4.dist-info/WHEEL
odoo12_addon_pos_order_line_note-12.0.1.0.4.dist-info/top_level.txt
odoo12_addon_pos_order_line_note-12.0.1.0.4.dist-info/RECORD
